open_llm_gateway/__init__.py
open_llm_gateway/llmgateway.py
open_llm_gateway/types.py
open_llm_gateway/providers/anthropic/gateway.py
open_llm_gateway/providers/azure/gateway.py
open_llm_gateway/providers/openai/gateway.py
open_llm_gateway/utils/logger.py
open_llm_gateway/utils/param_converters.py
open_llm_gateway-0.1.3.dist-info/LICENSE
open_llm_gateway-0.1.3.dist-info/METADATA
open_llm_gateway-0.1.3.dist-info/WHEEL
open_llm_gateway-0.1.3.dist-info/top_level.txt
open_llm_gateway-0.1.3.dist-info/RECORD
