Metadata-Version: 2.1
Name: open_llm_gateway
Version: 0.1.3
Summary: A Gateway for LLM API interactions
Home-page: https://github.com/ottic-ai/llm-gateway-python
Author: Dmitry Sergeev
Author-email: Dmitry Sergeev <dmitry@ottic.ai>
Project-URL: Homepage, https://github.com/ottic-ai/llm-gateway-python
Project-URL: Issues, https://github.com/ottic-ai/llm-gateway-python/issues
Classifier: Programming Language :: Python :: 3
Classifier: License :: OSI Approved :: MIT License
Classifier: Operating System :: OS Independent
Classifier: Development Status :: 4 - Beta
Classifier: Intended Audience :: Developers
Classifier: Topic :: Software Development :: Libraries :: Python Modules
Requires-Python: >=3.7
License-File: LICENSE
Requires-Dist: requests>=2.31.0
Requires-Dist: pydantic>=2.0.0
Requires-Dist: docstring_parser>=0.15
